[
  { "id": "en-love-001", "text": "You are my today and all of my tomorrows.", "tags": ["romantic"], "length": 46, "mood": "romantic", "lang": "en" },
  { "id": "en-love-002", "text": "Every love story is beautiful, but ours is my favorite.", "tags": ["romantic"], "length": 56, "mood": "romantic", "lang": "en" },
  { "id": "en-love-003", "text": "You stole my heart, but I’ll let you keep it.", "tags": ["cute"], "length": 44, "mood": "sweet", "lang": "en" },
  { "id": "en-love-004", "text": "I still fall for you every single day.", "tags": ["romantic"], "length": 40, "mood": "romantic", "lang": "en" },
  { "id": "en-love-005", "text": "Forever is not long enough with you.", "tags": ["romantic"], "length": 39, "mood": "romantic", "lang": "en" },
  { "id": "en-love-006", "text": "Your smile is my favorite place.", "tags": ["sweet"], "length": 34, "mood": "sweet", "lang": "en" },
  { "id": "en-love-007", "text": "Love is when the other person’s happiness is more important than yours.", "tags": ["deep"], "length": 76, "mood": "romantic", "lang": "en" },
  { "id": "en-love-008", "text": "You’re my paradise and I’d happily get lost in you.", "tags": ["romantic"], "length": 55, "mood": "romantic", "lang": "en" },
  { "id": "en-love-009", "text": "I love you more than words can define, feelings can express, and thoughts can imagine.", "tags": ["romantic","deep"], "length": 93, "mood": "romantic", "lang": "en" },
  { "id": "en-love-010", "text": "You’re my favorite notification.", "tags": ["cute","short"], "length": 31, "mood": "sweet", "lang": "en" },
  { "id": "en-love-011", "text": "Falling for you was the best decision I ever made.", "tags": ["romantic"], "length": 52, "mood": "romantic", "lang": "en" },
  { "id": "en-love-012", "text": "With you, every moment is magic.", "tags": ["romantic","short"], "length": 36, "mood": "romantic", "lang": "en" },
  { "id": "en-love-013", "text": "I didn’t believe in forever until I met you.", "tags": ["romantic"], "length": 47, "mood": "romantic", "lang": "en" },
  { "id": "en-love-014", "text": "My favorite place is inside your hug.", "tags": ["sweet"], "length": 40, "mood": "sweet", "lang": "en" },
  { "id": "en-love-015", "text": "I love you endlessly, hopelessly, and unconditionally.", "tags": ["romantic"], "length": 57, "mood": "romantic", "lang": "en" },
  { "id": "en-love-016", "text": "You are the poem I never knew how to write.", "tags": ["deep","romantic"], "length": 48, "mood": "romantic", "lang": "en" },
  { "id": "en-love-017", "text": "Even after all this time, you still give me butterflies.", "tags": ["romantic","cute"], "length": 58, "mood": "romantic", "lang": "en" },
  { "id": "en-love-018", "text": "Being with you feels like home.", "tags": ["short","sweet"], "length": 34, "mood": "sweet", "lang": "en" },
  { "id": "en-love-019", "text": "I choose you. And I’ll choose you, over and over.", "tags": ["romantic"], "length": 55, "mood": "romantic", "lang": "en" },
  { "id": "en-love-020", "text": "Every time I see you, I fall in love all over again.", "tags": ["romantic"], "length": 57, "mood": "romantic", "lang": "en" },
  { "id": "en-love-021", "text": "My heart beats faster when I hear your name.", "tags": ["romantic"], "length": 49, "mood": "romantic", "lang": "en" },
  { "id": "en-love-022", "text": "You are the missing piece I’ve been looking for.", "tags": ["romantic","deep"], "length": 53, "mood": "romantic", "lang": "en" },
  { "id": "en-love-023", "text": "Holding your hand feels like holding the world.", "tags": ["romantic"], "length": 52, "mood": "romantic", "lang": "en" },
  { "id": "en-love-024", "text": "You are the reason behind my favorite memories.", "tags": ["romantic"], "length": 55, "mood": "romantic", "lang": "en" },
  { "id": "en-love-025", "text": "No matter how much I say I love you, I always love you more than that.", "tags": ["romantic","deep"], "length": 78, "mood": "romantic", "lang": "en" },
  { "id": "en-love-026", "text": "I’d rather spend one lifetime with you than face all the ages alone.", "tags": ["romantic","deep"], "length": 74, "mood": "romantic", "lang": "en" },
  { "id": "en-love-027", "text": "Your voice is my favorite sound.", "tags": ["sweet"], "length": 36, "mood": "sweet", "lang": "en" },
  { "id": "en-love-028", "text": "Every love song reminds me of you.", "tags": ["romantic"], "length": 40, "mood": "romantic", "lang": "en" },
  { "id": "en-love-029", "text": "You are the best part of my every day.", "tags": ["romantic"], "length": 43, "mood": "romantic", "lang": "en" },
  { "id": "en-love-030", "text": "Life makes sense when I’m with you.", "tags": ["romantic"], "length": 41, "mood": "romantic", "lang": "en" }
]
